flatbush/__init__.py
flatbush/flatbush.py
flatbush-1.1.0.dist-info/LICENSE
flatbush-1.1.0.dist-info/METADATA
flatbush-1.1.0.dist-info/WHEEL
flatbush-1.1.0.dist-info/top_level.txt
flatbush-1.1.0.dist-info/RECORD
