Metadata-Version: 2.1
Name: flatbush
Version: 1.1.0
Summary: flatbush spatial index
Home-page: https://github.com/bmharper/flatbush-python
Author: Ben Harper
Author-email: rogojin@gmail.com
License: MIT
Platform: UNKNOWN
Classifier: Programming Language :: Python :: 3
Classifier: License :: OSI Approved :: MIT License
Classifier: Operating System :: OS Independent
Requires-Python: >=3.6
